fourier_grx.cpython-311-x86_64-linux-gnu.so
fourier_grx.pyi
fourier_grx-0.1.1.dist-info/METADATA
fourier_grx-0.1.1.dist-info/WHEEL
fourier_grx-0.1.1.dist-info/entry_points.txt
fourier_grx-0.1.1.dist-info/top_level.txt
fourier_grx-0.1.1.dist-info/RECORD
