Metadata-Version: 2.1
Name: fourier-grx
Version: 0.1.1
Summary: Robotics Control System for the General Robotics (GR)
Author-email: "Fourier Intelligence Ltd." <algorithm@fftai.com>, Xin Chen <xin.chen@fftai.com>, Yuxiang Gao <yuxiang.gao@fftai.com>
License: MIT
Requires-Python: ==3.11.*
Requires-Dist: numpy<2.0.0
Requires-Dist: pyyaml>=6.0.1
Requires-Dist: msgpack>=1.0.8
Requires-Dist: msgpack-numpy>=0.4.8
Requires-Dist: eclipse-zenoh==0.11.0rc3
Requires-Dist: typer>=0.12.3
Requires-Dist: rich>=13.7.1
Requires-Dist: loguru>=0.7.2
Requires-Dist: omegaconf>=2.3.0
Requires-Dist: pin-pink>=2.1.0
Requires-Dist: meshcat-shapes>=0.3.0
Requires-Dist: ischedule>=1.2.7
Requires-Dist: inputs>=0.5
Requires-Dist: fourier-core==0.1.1rc1
Requires-Dist: ruckig>=0.12.2
